[
  {
    "IT": [
      "Si"
    ],
    "FR": [
      "Oui"
    ],
    "RU": [
      "\u0414\u0430"
    ],
    "CA": [
      "S\u00ed"
    ],
    "PT": [
      "Sim"
    ],
    "ES": [
      "S\u00ed"
    ],
    "EN": [
      "Yes"
    ]
  },
  {
    "IT": [
      "No, Non"
    ],
    "FR": [
      "Ne, Non"
    ],
    "RU": [
      "\u041d\u0435, \u041d\u0435\u0442"
    ],
    "CA": [
      "No"
    ],
    "PT": [
      "N\u00e3o"
    ],
    "ES": [
      "No"
    ],
    "EN": [
      "No, Not"
    ]
  },
  {
    "IT": [
      "Benvenutto"
    ],
    "FR": [
      "Bienvenue"
    ],
    "RU": [
      "\u0414\u043e\u0431\u0440\u043e \u043f\u043e\u0436\u0430\u043b\u043e\u0432\u0430\u0442\u044c"
    ],
    "CA": [
      "Benvingut"
    ],
    "PT": [
      "Bemvindo"
    ],
    "ES": [
      "Bienvenido"
    ],
    "EN": [
      "Welcome"
    ]
  },
  {
    "IT": [
      "Pronto?"
    ],
    "FR": [
      "All\u00f4?"
    ],
    "RU": [
      "\u0410\u043b\u043b\u043e"
    ],
    "CA": [
      "Digui?"
    ],
    "PT": [
      "Oi? (Telefone)"
    ],
    "ES": [
      "Diga? (Tel\u00e9fono)"
    ],
    "EN": [
      "Hi, Hello (Telephone)"
    ]
  },
  {
    "IT": [
      "Ciao, Salve"
    ],
    "FR": [
      "All\u00f4, Salut"
    ],
    "RU": [
      "\u041f\u0440\u0438\u0432\u0435\u0442, \u0417\u0434\u0440\u0430\u0432\u0441\u0442\u0432\u0443\u0439\u0442\u0438\u0435"
    ],
    "CA": [
      "Hola"
    ],
    "PT": [
      "Oi, Ol\u00e1"
    ],
    "ES": [
      "Hola"
    ],
    "EN": [
      "Hi, Hello"
    ]
  },
  {
    "IT": [
      "Buongiorno"
    ],
    "FR": [
      "Bonjour"
    ],
    "RU": [
      "\u0414\u043e\u0431\u0440\u0438\u0439 \u0414\u0435\u043d\u044c"
    ],
    "CA": [
      "Bon d\u00eda"
    ],
    "PT": [
      "Bom dia"
    ],
    "ES": [
      "Buen d\u00eda"
    ],
    "EN": [
      "Good day"
    ]
  },
  {
    "IT": [
      "Buona mattina"
    ],
    "FR": [
      "Bonjour (\u041catin)"
    ],
    "RU": [
      "\u0414\u043e\u0431\u0440\u043e\u0435 \u0443\u0442\u0440\u043e"
    ],
    "CA": [
      "Bona matinada"
    ],
    "PT": [
      "Bom dia (\u041canh\u00e3)"
    ],
    "ES": [
      "Buenos d\u00edas"
    ],
    "EN": [
      "Good morning"
    ]
  },
  {
    "IT": [
      "Buon pomeriggio, Buonasera"
    ],
    "FR": [
      "Bonne apr\u00e8s-midi, Bonsoir"
    ],
    "RU": [
      "\u0414\u043e\u0431\u0440\u0438\u0439 \u0412\u0435\u0447\u0435\u0440"
    ],
    "CA": [
      "Bona tarda"
    ],
    "PT": [
      "Boa tarde"
    ],
    "ES": [
      "Buenas tardes"
    ],
    "EN": [
      "Good afternoon, Good evening"
    ]
  },
  {
    "IT": [
      "Buona notte"
    ],
    "FR": [
      "Bonne nuit"
    ],
    "RU": [
      "\u0421\u043f\u043e\u043a\u043e\u0439\u043d\u043e\u0439 \u041d\u043e\u0447\u0438"
    ],
    "CA": [
      "Bona nit"
    ],
    "PT": [
      "Boa noite"
    ],
    "ES": [
      "Buenas noches"
    ],
    "EN": [
      "Good night"
    ]
  },
  {
    "IT": [
      "Ciao, Addio"
    ],
    "FR": [
      "Adieu"
    ],
    "RU": [
      "\u041f\u043e\u043a\u0430"
    ],
    "CA": [
      "Ad\u00e9u"
    ],
    "PT": [
      "Adeus"
    ],
    "ES": [
      "Adi\u00f3s"
    ],
    "EN": [
      "Bye, Goodbye"
    ]
  },
  {
    "IT": [
      "Ci vediamo pi\u00f9 tardi"
    ],
    "FR": [
      "\u00c0 plus tard"
    ],
    "RU": [
      "\u0414\u043e \u0441\u043a\u043e\u0440\u043e\u0433\u043e"
    ],
    "CA": [
      "Fins despr\u00e9s"
    ],
    "PT": [
      "At\u00e9 logo"
    ],
    "ES": [
      "Hasta luego"
    ],
    "EN": [
      "See you later"
    ]
  },
  {
    "IT": [
      "Arrivederci"
    ],
    "FR": [
      "Au revoir"
    ],
    "RU": [
      "\u0414\u043e \u0441\u0432\u0438\u0434\u0430\u043d\u044f"
    ],
    "CA": [
      "Ens veiem despr\u00e9s"
    ],
    "PT": [
      "At\u00e9 a vista"
    ],
    "ES": [
      "Hasta la vista"
    ],
    "EN": [
      "See you"
    ]
  },
  {
    "IT": [
      "Scusi"
    ],
    "FR": [
      "Pardon"
    ],
    "RU": [
      "\u0418\u0437\u0432\u0438\u043d\u0438\u0442\u0435 (\u0412\u043d\u0438\u043c\u0430\u043d\u0438\u0435)"
    ],
    "CA": [
      "Perd\u00f2"
    ],
    "PT": [
      "Licen\u00e7a"
    ],
    "ES": [
      "Perd\u00f3n (Atenci\u00f3n)"
    ],
    "EN": [
      "Excuse me"
    ]
  },
  {
    "IT": [
      "Scusi, Spiacente"
    ],
    "FR": [
      "Pardon, D\u00e9sol\u00e9"
    ],
    "RU": [
      "\u0418\u0437\u0432\u0438\u043d\u0438\u0442\u0435"
    ],
    "CA": [
      "Perd\u00f2, Disculpi"
    ],
    "PT": [
      "Desculpe"
    ],
    "ES": [
      "Perd\u00f3n (Disculpa)"
    ],
    "EN": [
      "Sorry"
    ]
  },
  {
    "IT": [
      "Prego, Per favore"
    ],
    "FR": [
      "S'il vous plait"
    ],
    "RU": [
      "\u041f\u043e\u0436\u0430\u043b\u0443\u0439\u0441\u0442\u0430"
    ],
    "CA": [
      "Si us plau"
    ],
    "PT": [
      "Por favor"
    ],
    "ES": [
      "Por favor"
    ],
    "EN": [
      "Please"
    ]
  },
  {
    "IT": [
      "Grazie"
    ],
    "FR": [
      "Merci"
    ],
    "RU": [
      "\u0421\u043f\u0430\u0441\u0438\u0431\u043e, \u0411\u043b\u0430\u0433\u043e\u0434\u0430\u0440\u044e"
    ],
    "CA": [
      "Gr\u00e0cies"
    ],
    "PT": [
      "Obrigado, Obrigada"
    ],
    "ES": [
      "Gracias"
    ],
    "EN": [
      "Thanks, Thank you"
    ]
  },
  {
    "IT": [
      "Prego, Di niente"
    ],
    "FR": [
      "De rien"
    ],
    "RU": [
      "\u041f\u043e\u0436\u0430\u043b\u0443\u0439\u0441\u0442\u0430, \u041d\u0435 \u0437\u0430 \u0447\u0442\u043e"
    ],
    "CA": [
      "De res"
    ],
    "PT": [
      "De nada"
    ],
    "ES": [
      "De nada"
    ],
    "EN": [
      "You are welcome"
    ]
  },
  {
    "IT": [
      "Complimenti"
    ],
    "FR": [
      "F\u00e9licitations"
    ],
    "RU": [
      "\u041f\u043e\u0437\u0434\u0440\u0430\u0432\u043b\u0435\u043d\u0438\u044f"
    ],
    "CA": [
      "Felicitacions"
    ],
    "PT": [
      "Parab\u00e9ns"
    ],
    "ES": [
      "Felicidades"
    ],
    "EN": [
      "Congratulations"
    ]
  },
  {
    "IT": [
      "Che?, Cosa?"
    ],
    "FR": [
      "Quoi?"
    ],
    "RU": [
      "\u0427\u0442\u043e?"
    ],
    "CA": [
      "Qu\u00e9?"
    ],
    "PT": [
      "O que?"
    ],
    "ES": [
      "Qu\u00e9?"
    ],
    "EN": [
      "What?"
    ]
  },
  {
    "IT": [
      "Come?"
    ],
    "FR": [
      "Comment?"
    ],
    "RU": [
      "\u041a\u0430\u043a?"
    ],
    "CA": [
      "Com?"
    ],
    "PT": [
      "Como?"
    ],
    "ES": [
      "C\u00f3mo?"
    ],
    "EN": [
      "How?"
    ]
  },
  {
    "IT": [
      "Quanto?, Quanta?"
    ],
    "FR": [
      "Combien?"
    ],
    "RU": [
      "\u0421\u043a\u043e\u043b\u044c\u043a\u043e?"
    ],
    "CA": [
      "Quant?, Quanta?"
    ],
    "PT": [
      "Quanto?, Quanta?"
    ],
    "ES": [
      "Cu\u00e1nto?, Cu\u00e1nta?"
    ],
    "EN": [
      "How much? How many?"
    ]
  },
  {
    "IT": [
      "Perch\u00e9?"
    ],
    "FR": [
      "Pourquoi?"
    ],
    "RU": [
      "\u041f\u043e\u0447\u0435\u043c\u0443?, \u0417\u0430\u0447\u0435\u043c?"
    ],
    "CA": [
      "Per qu\u00e8?"
    ],
    "PT": [
      "Por que?"
    ],
    "ES": [
      "Por qu\u00e9?"
    ],
    "EN": [
      "Why?"
    ]
  },
  {
    "IT": [
      "Perch\u00e9"
    ],
    "FR": [
      "Parce que"
    ],
    "RU": [
      "\u041f\u043e\u0442\u043e\u043c\u0443 \u0447\u0442\u043e"
    ],
    "CA": [
      "Perqu\u00e8"
    ],
    "PT": [
      "Porque"
    ],
    "ES": [
      "Porque"
    ],
    "EN": [
      "Because"
    ]
  },
  {
    "IT": [
      "Dove?"
    ],
    "FR": [
      "O\u00f9?"
    ],
    "RU": [
      "\u0413\u0434\u0435?"
    ],
    "CA": [
      "On?"
    ],
    "PT": [
      "Onde?"
    ],
    "ES": [
      "D\u00f3nde?"
    ],
    "EN": [
      "Where?"
    ]
  },
  {
    "IT": [
      "Quando?"
    ],
    "FR": [
      "Quand?"
    ],
    "RU": [
      "\u041a\u043e\u0433\u0434\u0430?"
    ],
    "CA": [
      "Quan?"
    ],
    "PT": [
      "Quando?"
    ],
    "ES": [
      "Cu\u00e1ndo?"
    ],
    "EN": [
      "When?"
    ]
  },
  {
    "IT": [
      "Qual?"
    ],
    "FR": [
      "Lequel, Laquelle"
    ],
    "RU": [
      "\u041a\u0430\u043a\u043e\u0439?"
    ],
    "CA": [
      "Quin?"
    ],
    "PT": [
      "Qual?"
    ],
    "ES": [
      "Cu\u00e1l?"
    ],
    "EN": [
      "Which?"
    ]
  },
  {
    "IT": [
      "Chi?"
    ],
    "FR": [
      "Qui?"
    ],
    "RU": [
      "\u041a\u0442\u043e?"
    ],
    "CA": [
      "Qui?"
    ],
    "PT": [
      "Quem?"
    ],
    "ES": [
      "Qui\u00e9n?"
    ],
    "EN": [
      "Who?"
    ]
  },
  {
    "IT": [
      "Domanda",
      "F"
    ],
    "FR": [
      "Question",
      "F"
    ],
    "RU": [
      "\u0412\u043e\u043f\u0440\u043e\u0441",
      "M"
    ],
    "CA": [
      "Pregunta, Q\u00fcesti\u00f3",
      "F"
    ],
    "PT": [
      "Pergunta, Quest\u00e3o",
      "F"
    ],
    "ES": [
      "Pregunta, Questi\u00f3n",
      "F"
    ],
    "EN": [
      "Question"
    ]
  },
  {
    "IT": [
      "Risposta",
      "F"
    ],
    "FR": [
      "R\u00e9ponse",
      "F"
    ],
    "RU": [
      "\u041e\u0442\u0432\u0435\u0442",
      "M"
    ],
    "CA": [
      "Resposta",
      "F"
    ],
    "PT": [
      "Resposta, Contesta\u00e7\u00e3o",
      "F"
    ],
    "ES": [
      "Respuesta",
      "F"
    ],
    "EN": [
      "Answer, Response"
    ]
  },
  {
    "IT": [
      "Uomo",
      "M"
    ],
    "FR": [
      "Homme",
      "M"
    ],
    "RU": [
      "\u041c\u0443\u0447\u0449\u0438\u043d\u0430",
      "M"
    ],
    "CA": [
      "Home",
      "M"
    ],
    "PT": [
      "Homem",
      "M"
    ],
    "ES": [
      "Hombre",
      "M"
    ],
    "EN": [
      "Man"
    ]
  },
  {
    "IT": [
      "Donna",
      "F"
    ],
    "FR": [
      "Femme",
      "F"
    ],
    "RU": [
      "\u0416\u0435\u043d\u0449\u0438\u043d\u0430",
      "F"
    ],
    "CA": [
      "Dona",
      "F"
    ],
    "PT": [
      "Mulher",
      "F"
    ],
    "ES": [
      "Mujer",
      "F"
    ],
    "EN": [
      "Woman"
    ]
  },
  {
    "IT": [
      "Ragazzo",
      "M"
    ],
    "FR": [
      "Gar\u00e7on",
      "M"
    ],
    "RU": [
      "\u041c\u0430\u043b\u044c\u0447\u0438\u043a",
      "M"
    ],
    "CA": [
      "Noi",
      "M"
    ],
    "PT": [
      "Garoto",
      "M"
    ],
    "ES": [
      "Chico",
      "M"
    ],
    "EN": [
      "Boy"
    ]
  },
  {
    "IT": [
      "Ragazza",
      "F"
    ],
    "FR": [
      "Fille",
      "F"
    ],
    "RU": [
      "\u0414\u0435\u0432\u043e\u0447\u043a\u0430",
      "F"
    ],
    "CA": [
      "Noia",
      "F"
    ],
    "PT": [
      "Garota",
      "F"
    ],
    "ES": [
      "Chica",
      "F"
    ],
    "EN": [
      "Girl"
    ]
  },
  {
    "IT": [
      "Bambino, Bambina"
    ],
    "FR": [
      "Enfant",
      "M"
    ],
    "RU": [
      "\u0420\u0435\u0431\u0435\u043d\u043e\u043a, \u0414\u0438\u0442\u044f",
      "M"
    ],
    "CA": [
      "Nen, Nena"
    ],
    "PT": [
      "Crian\u00e7a",
      "F"
    ],
    "ES": [
      "Ni\u00f1o, Cr\u00edo"
    ],
    "EN": [
      "Child"
    ]
  },
  {
    "IT": [
      "Bambini",
      "M"
    ],
    "FR": [
      "Enfants",
      "M"
    ],
    "RU": [
      "\u0414\u0435\u0442\u0438"
    ],
    "CA": [
      "Nens",
      "M"
    ],
    "PT": [
      "Crian\u00e7as",
      "F"
    ],
    "ES": [
      "Cr\u00edos",
      "M"
    ],
    "EN": [
      "Children"
    ]
  },
  {
    "FR": [
      "B\u00e9b\u00e9",
      "M"
    ],
    "ES": [
      "Beb\u00e9",
      "M"
    ],
    "CA": [
      "Nad\u00f3, Nadona",
      "M"
    ],
    "PT": [
      "Beb\u00ea",
      "M"
    ],
    "EN": [
      "Baby"
    ]
  },
  {
    "IT": [
      "Pap\u00e0",
      "M"
    ],
    "FR": [
      "Papa",
      "M"
    ],
    "RU": [
      "\u041f\u0430\u043f\u0430",
      "M"
    ],
    "CA": [
      "Pap\u00e0",
      "M"
    ],
    "PT": [
      "Pai (Meu)",
      "M"
    ],
    "ES": [
      "Pap\u00e1",
      "M"
    ],
    "EN": [
      "Dad"
    ]
  },
  {
    "IT": [
      "Mamma",
      "F"
    ],
    "FR": [
      "Mamman",
      "F"
    ],
    "RU": [
      "\u041c\u0430\u043c\u0430",
      "F"
    ],
    "CA": [
      "Mam\u00e0",
      "F"
    ],
    "PT": [
      "M\u00e3e (Minha)",
      "F"
    ],
    "ES": [
      "Mam\u00e1",
      "F"
    ],
    "EN": [
      "Mom"
    ]
  },
  {
    "IT": [
      "Padre",
      "M"
    ],
    "FR": [
      "P\u00e8re",
      "M"
    ],
    "RU": [
      "\u041e\u0442\u0435\u0446",
      "M"
    ],
    "CA": [
      "Pare",
      "M"
    ],
    "PT": [
      "Pai",
      "M"
    ],
    "ES": [
      "Padre",
      "M"
    ],
    "EN": [
      "Father"
    ]
  },
  {
    "IT": [
      "Madre",
      "F"
    ],
    "FR": [
      "M\u00e8re",
      "F"
    ],
    "RU": [
      "\u041c\u0430\u0442\u044c",
      "F"
    ],
    "CA": [
      "Mare",
      "F"
    ],
    "PT": [
      "M\u00e3e",
      "F"
    ],
    "ES": [
      "Madre",
      "F"
    ],
    "EN": [
      "Mother"
    ]
  },
  {
    "IT": [
      "Nonno",
      "M"
    ],
    "FR": [
      "Grand-p\u00e8re",
      "M"
    ],
    "RU": [
      "\u0414\u0435\u0434\u0443\u0448\u043a\u0430",
      "M"
    ],
    "CA": [
      "Avi",
      "M"
    ],
    "PT": [
      "Av\u00f4",
      "M"
    ],
    "ES": [
      "Abuelo",
      "M"
    ],
    "EN": [
      "Grandfather"
    ]
  },
  {
    "IT": [
      "Nonna",
      "F"
    ],
    "FR": [
      "Grand-m\u00e8re",
      "F"
    ],
    "RU": [
      "\u0411\u0430\u0431\u0443\u0448\u043a\u0430",
      "F"
    ],
    "CA": [
      "\u00c0via",
      "F"
    ],
    "PT": [
      "Av\u00f3",
      "F"
    ],
    "ES": [
      "Abuela",
      "F"
    ],
    "EN": [
      "Grandmother"
    ]
  },
  {
    "IT": [
      "Figlio",
      "M"
    ],
    "FR": [
      "Fils (Mon)",
      "M"
    ],
    "RU": [
      "\u0421\u044b\u043d",
      "M"
    ],
    "CA": [
      "Fill",
      "M"
    ],
    "PT": [
      "Filho",
      "M"
    ],
    "ES": [
      "Hijo",
      "M"
    ],
    "EN": [
      "Son"
    ]
  },
  {
    "IT": [
      "Figlia",
      "F"
    ],
    "FR": [
      "Fille (Ma)",
      "F"
    ],
    "RU": [
      "\u0414\u043e\u0447\u044c",
      "F"
    ],
    "CA": [
      "Filla",
      "F"
    ],
    "PT": [
      "Filha",
      "F"
    ],
    "ES": [
      "Hija",
      "F"
    ],
    "EN": [
      "Daughter"
    ]
  },
  {
    "IT": [
      "Sorello",
      "M"
    ],
    "FR": [
      "Fr\u00e8re",
      "M"
    ],
    "RU": [
      "\u0411\u0440\u0430\u0442",
      "M"
    ],
    "CA": [
      "Germ\u00e0",
      "M"
    ],
    "PT": [
      "Irm\u00e3o",
      "M"
    ],
    "ES": [
      "Hermano",
      "M"
    ],
    "EN": [
      "Brother"
    ]
  },
  {
    "IT": [
      "Sorella",
      "F"
    ],
    "FR": [
      "Soeur",
      "F"
    ],
    "RU": [
      "\u0421\u0435\u0441\u0442\u0440\u0430",
      "F"
    ],
    "CA": [
      "Germana",
      "F"
    ],
    "PT": [
      "Irm\u00e3",
      "F"
    ],
    "ES": [
      "Hermana",
      "F"
    ],
    "EN": [
      "Sister"
    ]
  },
  {
    "IT": [
      "Fidanzato",
      "M"
    ],
    "FR": [
      "Copain",
      "M"
    ],
    "RU": [
      "\u0414\u0440\u0443\u0436\u043e\u043a",
      "M"
    ],
    "CA": [
      "Nuvi",
      "M"
    ],
    "PT": [
      "Namorado",
      "M"
    ],
    "ES": [
      "Novio",
      "M"
    ],
    "EN": [
      "Boyfriend, Fianc"
    ]
  },
  {
    "IT": [
      "Fidanzata",
      "F"
    ],
    "FR": [
      "Copine",
      "F"
    ],
    "RU": [
      "\u041f\u043e\u0434\u0440\u0443\u0433\u0430",
      "F"
    ],
    "CA": [
      "N\u00favia",
      "F"
    ],
    "PT": [
      "Namorada",
      "F"
    ],
    "ES": [
      "Novia",
      "F"
    ],
    "EN": [
      "Girlfriend"
    ]
  },
  {
    "IT": [
      "Marito",
      "M"
    ],
    "FR": [
      "Mari",
      "M"
    ],
    "RU": [
      "\u041c\u0443\u0436",
      "M"
    ],
    "CA": [
      "Marit",
      "M"
    ],
    "PT": [
      "Esposo, Marido",
      "M"
    ],
    "ES": [
      "Esposo, Marido",
      "M"
    ],
    "EN": [
      "Husband"
    ]
  },
  {
    "IT": [
      "Moglie, Donna",
      "F"
    ],
    "FR": [
      "Femme, \u00c9pouse",
      "F"
    ],
    "RU": [
      "\u0416\u0435\u043d\u0430",
      "F"
    ],
    "CA": [
      "Esposa, Dona",
      "F"
    ],
    "PT": [
      "Esposa, Mulher",
      "F"
    ],
    "ES": [
      "Esposa, Mujer",
      "F"
    ],
    "EN": [
      "Wife"
    ]
  },
  {
    "IT": [
      "Signore",
      "M"
    ],
    "FR": [
      "Monsieur",
      "M"
    ],
    "RU": [
      "\u0421\u044d\u0440, \u0414\u0436\u0435\u043d\u0442\u043b\u044c\u043c\u0435\u043d",
      "M"
    ],
    "CA": [
      "Senyor",
      "M"
    ],
    "PT": [
      "Senhor, Cavalheiro",
      "M"
    ],
    "ES": [
      "Se\u00f1or, Don, Caballero",
      "M"
    ],
    "EN": [
      "Sir, Gentleman"
    ]
  },
  {
    "IT": [
      "Signora",
      "F"
    ],
    "FR": [
      "Madame, Dame",
      "F"
    ],
    "RU": [
      "\u041c\u0430\u0434\u0430\u043c, \u041b\u0435\u0434\u0438, \u0414\u0430\u043c\u0430",
      "F"
    ],
    "CA": [
      "Senyora",
      "F"
    ],
    "PT": [
      "Senhora, Dona",
      "F"
    ],
    "ES": [
      "Se\u00f1ora, Do\u00f1a, Dama",
      "F"
    ],
    "EN": [
      "Lady, Madam, Dame"
    ]
  },
  {
    "IT": [
      "Signorina",
      "F"
    ],
    "FR": [
      "Mademoiselle",
      "F"
    ],
    "RU": [
      "\u041c\u0438\u0441\u0441",
      "F"
    ],
    "CA": [
      "Senyoreta",
      "F"
    ],
    "PT": [
      "Senhorita",
      "F"
    ],
    "ES": [
      "Se\u00f1orita",
      "F"
    ],
    "EN": [
      "Miss"
    ]
  },
  {
    "IT": [
      "Amico",
      "M"
    ],
    "FR": [
      "Ami",
      "M"
    ],
    "RU": [
      "\u0414\u0440\u0443\u0433",
      "M"
    ],
    "CA": [
      "Amic",
      "M"
    ],
    "PT": [
      "Amigo",
      "M"
    ],
    "ES": [
      "Amigo",
      "M"
    ],
    "EN": [
      "Friend"
    ]
  },
  {
    "IT": [
      "Persona",
      "F"
    ],
    "FR": [
      "Personne",
      "F"
    ],
    "RU": [
      "\u0427\u0435\u043b\u043e\u0432\u0435\u043a",
      "M"
    ],
    "CA": [
      "Persona",
      "F"
    ],
    "PT": [
      "Pessoa",
      "F"
    ],
    "ES": [
      "Persona",
      "F"
    ],
    "EN": [
      "Person"
    ]
  },
  {
    "IT": [
      "Gente",
      "F"
    ],
    "FR": [
      "Gens",
      "F"
    ],
    "RU": [
      "\u041b\u044e\u0434\u0438"
    ],
    "CA": [
      "Gent",
      "F"
    ],
    "PT": [
      "Gente",
      "F"
    ],
    "ES": [
      "Gente",
      "F"
    ],
    "EN": [
      "People"
    ]
  },
  {
    "IT": [
      "Zero"
    ],
    "FR": [
      "Z\u00e9ro"
    ],
    "RU": [
      "\u043d\u0443\u043b\u044c"
    ],
    "CA": [
      "Zero"
    ],
    "PT": [
      "Zero"
    ],
    "ES": [
      "Cero"
    ],
    "EN": [
      "Zero"
    ]
  },
  {
    "IT": [
      "Uno"
    ],
    "FR": [
      "Un"
    ],
    "RU": [
      "\u041e\u0434\u0438\u043d"
    ],
    "CA": [
      "Un"
    ],
    "PT": [
      "Um"
    ],
    "ES": [
      "Uno"
    ],
    "EN": [
      "One"
    ]
  },
  {
    "IT": [
      "Due"
    ],
    "FR": [
      "Deux"
    ],
    "RU": [
      "\u0414\u0432\u0430"
    ],
    "CA": [
      "Dos"
    ],
    "PT": [
      "Dois"
    ],
    "ES": [
      "Dos"
    ],
    "EN": [
      "Two"
    ]
  },
  {
    "IT": [
      "Tre"
    ],
    "FR": [
      "Trois"
    ],
    "RU": [
      "\u0422\u0440\u0438"
    ],
    "CA": [
      "Tres"
    ],
    "PT": [
      "Tr\u00eas"
    ],
    "ES": [
      "Tres"
    ],
    "EN": [
      "Three"
    ]
  },
  {
    "IT": [
      "Quattro"
    ],
    "FR": [
      "Quatre"
    ],
    "RU": [
      "\u0427\u0435\u0442\u044b\u0440\u0435"
    ],
    "CA": [
      "Quatre"
    ],
    "PT": [
      "Quatro"
    ],
    "ES": [
      "Cuatro"
    ],
    "EN": [
      "Four"
    ]
  },
  {
    "IT": [
      "Cinque"
    ],
    "FR": [
      "Cinq"
    ],
    "RU": [
      "\u041f\u044f\u0442\u044c"
    ],
    "CA": [
      "Cinc"
    ],
    "PT": [
      "Cinco"
    ],
    "ES": [
      "Cinco"
    ],
    "EN": [
      "Five"
    ]
  },
  {
    "IT": [
      "Sei"
    ],
    "FR": [
      "Six"
    ],
    "RU": [
      "\u0428\u0435\u0441\u0442\u044c"
    ],
    "CA": [
      "Sis"
    ],
    "PT": [
      "Seis"
    ],
    "ES": [
      "Seis"
    ],
    "EN": [
      "Six"
    ]
  },
  {
    "IT": [
      "Sette"
    ],
    "FR": [
      "Sept"
    ],
    "RU": [
      "\u0421\u0435\u043c\u044c"
    ],
    "CA": [
      "Set"
    ],
    "PT": [
      "Sete"
    ],
    "ES": [
      "Siete"
    ],
    "EN": [
      "Seven"
    ]
  },
  {
    "IT": [
      "Otto"
    ],
    "FR": [
      "Huit"
    ],
    "RU": [
      "\u0412\u043e\u0441\u0435\u043c\u044c"
    ],
    "CA": [
      "Vuit"
    ],
    "PT": [
      "Oito"
    ],
    "ES": [
      "Ocho"
    ],
    "EN": [
      "Eight"
    ]
  },
  {
    "IT": [
      "Nove"
    ],
    "FR": [
      "Neuf"
    ],
    "RU": [
      "\u0414\u0435\u0432\u044f\u0442\u044c"
    ],
    "CA": [
      "Nou"
    ],
    "PT": [
      "Nove"
    ],
    "ES": [
      "Nueve"
    ],
    "EN": [
      "Nine"
    ]
  },
  {
    "IT": [
      "Dieci"
    ],
    "FR": [
      "Dix"
    ],
    "RU": [
      "\u0414\u0435\u0441\u044f\u0442\u044c"
    ],
    "CA": [
      "Deu"
    ],
    "PT": [
      "Dez"
    ],
    "ES": [
      "Diez"
    ],
    "EN": [
      "Ten"
    ]
  },
  {
    "IT": [
      "Undici"
    ],
    "FR": [
      "Onze"
    ],
    "RU": [
      "\u041e\u0434\u0438\u043d\u043d\u0430\u0434\u0446\u0430\u0442\u044c"
    ],
    "CA": [
      "Onze"
    ],
    "PT": [
      "Onze"
    ],
    "ES": [
      "Once"
    ],
    "EN": [
      "Eleven"
    ]
  },
  {
    "IT": [
      "Dodici"
    ],
    "FR": [
      "Douze"
    ],
    "RU": [
      "\u0414\u0432\u0435\u043d\u0430\u0434\u0446\u0430\u0442\u044c"
    ],
    "CA": [
      "Dotze"
    ],
    "PT": [
      "Doze"
    ],
    "ES": [
      "Doce"
    ],
    "EN": [
      "Twelve"
    ]
  },
  {
    "IT": [
      "Tredici"
    ],
    "FR": [
      "Treize"
    ],
    "RU": [
      "\u0422\u0440\u0438\u043d\u0430\u0434\u0446\u0430\u0442\u044c"
    ],
    "CA": [
      "Tretze"
    ],
    "PT": [
      "Treze"
    ],
    "ES": [
      "Trece"
    ],
    "EN": [
      "Thirteen"
    ]
  },
  {
    "IT": [
      "Quattordici"
    ],
    "FR": [
      "Quatorze"
    ],
    "RU": [
      "\u0427\u0435\u0442\u044b\u0440\u043d\u0430\u0434\u0446\u0430\u0442\u044c"
    ],
    "CA": [
      "Catorze"
    ],
    "PT": [
      "Quatorze"
    ],
    "ES": [
      "Catorce"
    ],
    "EN": [
      "Fourteen"
    ]
  },
  {
    "IT": [
      "Quindici"
    ],
    "FR": [
      "Quinze"
    ],
    "RU": [
      "\u041f\u044f\u0442\u043d\u0430\u0434\u0446\u0430\u0442\u044c"
    ],
    "CA": [
      "Quinze"
    ],
    "PT": [
      "Quinze"
    ],
    "ES": [
      "Quince"
    ],
    "EN": [
      "Fifteen"
    ]
  },
  {
    "IT": [
      "Sedici"
    ],
    "FR": [
      "Seize"
    ],
    "RU": [
      "\u0428\u0435\u0441\u0442\u043d\u0430\u0434\u0446\u0430\u0442\u044c"
    ],
    "CA": [
      "Setze"
    ],
    "PT": [
      "Dezesseis"
    ],
    "ES": [
      "Diecis\u00e9is"
    ],
    "EN": [
      "Sixteen"
    ]
  },
  {
    "IT": [
      "Diciassette"
    ],
    "FR": [
      "Dix-sept"
    ],
    "RU": [
      "\u0421\u0435\u043c\u043d\u0430\u0434\u0446\u0430\u0442\u044c"
    ],
    "CA": [
      "Disset"
    ],
    "PT": [
      "Dezessete"
    ],
    "ES": [
      "Diecisiete"
    ],
    "EN": [
      "Seventeen"
    ]
  },
  {
    "IT": [
      "Diciotto"
    ],
    "FR": [
      "Dix-huit"
    ],
    "RU": [
      "\u0412\u043e\u0441\u0435\u043c\u043d\u0430\u0434\u0446\u0430\u0442\u044c"
    ],
    "CA": [
      "Divuit"
    ],
    "PT": [
      "Dezoito"
    ],
    "ES": [
      "Dieciocho"
    ],
    "EN": [
      "Eighteen"
    ]
  },
  {
    "IT": [
      "Diciannove"
    ],
    "FR": [
      "Dix-neuf"
    ],
    "RU": [
      "\u0414\u0435\u0432\u044f\u0442\u043d\u0430\u0434\u0446\u0430\u0442\u044c"
    ],
    "CA": [
      "Dinou"
    ],
    "PT": [
      "Dezenove"
    ],
    "ES": [
      "Diecinueve"
    ],
    "EN": [
      "Nineteen"
    ]
  },
  {
    "IT": [
      "Venti"
    ],
    "FR": [
      "Vingt"
    ],
    "RU": [
      "\u0414\u0432\u0430\u0434\u0446\u0430\u0442\u044c"
    ],
    "CA": [
      "Vint"
    ],
    "PT": [
      "Vinte"
    ],
    "ES": [
      "Veinte"
    ],
    "EN": [
      "Twenty"
    ]
  },
  {
    "IT": [
      "Trenta"
    ],
    "FR": [
      "Trente"
    ],
    "RU": [
      "\u0422\u0440\u0438\u0434\u0446\u0430\u0442\u044c"
    ],
    "CA": [
      "Trenta"
    ],
    "PT": [
      "Trinta"
    ],
    "ES": [
      "Treinta"
    ],
    "EN": [
      "Thirty"
    ]
  },
  {
    "IT": [
      "Quaranta"
    ],
    "FR": [
      "Quarante"
    ],
    "RU": [
      "\u0421\u043e\u0440\u043e\u043a"
    ],
    "CA": [
      "Quaranta"
    ],
    "PT": [
      "Quarenta"
    ],
    "ES": [
      "Cuarenta"
    ],
    "EN": [
      "Fourty"
    ]
  },
  {
    "IT": [
      "Cinquanta"
    ],
    "FR": [
      "Cinquante"
    ],
    "RU": [
      "\u041f\u044f\u0442\u044c\u0434\u0435\u0441\u044f\u0442"
    ],
    "CA": [
      "Cinquata"
    ],
    "PT": [
      "Cinqueta"
    ],
    "ES": [
      "Cincueta"
    ],
    "EN": [
      "Fifty"
    ]
  },
  {
    "IT": [
      "Sessanta"
    ],
    "FR": [
      "Soixante"
    ],
    "RU": [
      "\u0428\u0435\u0441\u0442\u044c\u0434\u0435\u0441\u044f\u0442"
    ],
    "CA": [
      "Seixanta"
    ],
    "PT": [
      "Sessenta"
    ],
    "ES": [
      "Sesenta"
    ],
    "EN": [
      "Sixty"
    ]
  },
  {
    "IT": [
      "Settanta"
    ],
    "FR": [
      "Soixante-dix"
    ],
    "RU": [
      "\u0421\u0435\u043c\u044c\u0434\u0435\u0441\u044f\u0442"
    ],
    "CA": [
      "Setanta"
    ],
    "PT": [
      "Setenta"
    ],
    "ES": [
      "Setenta"
    ],
    "EN": [
      "Seventy"
    ]
  },
  {
    "IT": [
      "Ottanta"
    ],
    "FR": [
      "Quatre-vingts"
    ],
    "RU": [
      "\u0412\u043e\u0441\u0435\u043c\u044c\u0434\u0435\u0441\u044f\u0442"
    ],
    "CA": [
      "Vuitanta"
    ],
    "PT": [
      "Oitenta"
    ],
    "ES": [
      "Ochenta"
    ],
    "EN": [
      "Eighty"
    ]
  },
  {
    "IT": [
      "Novanta"
    ],
    "FR": [
      "Quatre-vingt-dix"
    ],
    "RU": [
      "\u0414\u0435\u0432\u044f\u043d\u043e\u0441\u0442\u043e"
    ],
    "CA": [
      "Noranta"
    ],
    "PT": [
      "Noventa"
    ],
    "ES": [
      "Noventa"
    ],
    "EN": [
      "Ninety"
    ]
  },
  {
    "IT": [
      "Cento"
    ],
    "FR": [
      "Cent"
    ],
    "RU": [
      "\u0421\u0442\u043e"
    ],
    "CA": [
      "Cent"
    ],
    "PT": [
      "Cem"
    ],
    "ES": [
      "Cien"
    ],
    "EN": [
      "Hundred"
    ]
  },
  {
    "IT": [
      "Mille"
    ],
    "FR": [
      "Mille"
    ],
    "RU": [
      "\u0422\u044b\u0441\u044f\u0447\u0430",
      "F"
    ],
    "CA": [
      "Mil"
    ],
    "PT": [
      "Mil"
    ],
    "ES": [
      "Mil"
    ],
    "EN": [
      "Thousand"
    ]
  },
  {
    "IT": [
      "Milione"
    ],
    "FR": [
      "Million"
    ],
    "RU": [
      "\u041c\u0438\u043b\u043b\u0438\u043e\u043d"
    ],
    "CA": [
      "Mili\u00f3"
    ],
    "PT": [
      "Milh\u00e3o"
    ],
    "ES": [
      "Mill\u00f3n"
    ],
    "EN": [
      "Million"
    ]
  },
  {
    "IT": [
      "Qui"
    ],
    "FR": [
      "Ici"
    ],
    "RU": [
      "\u0417\u0434\u0435\u0441\u044c, \u0412\u043e\u0442"
    ],
    "CA": [
      "Aqu\u00ed"
    ],
    "PT": [
      "Aqu\u00ed"
    ],
    "ES": [
      "Aqu\u00ed"
    ],
    "EN": [
      "Here"
    ]
  },
  {
    "IT": [
      "L\u00e0"
    ],
    "FR": [
      "L\u00e0"
    ],
    "RU": [
      "\u0422\u0430\u043c"
    ],
    "CA": [
      "Enll\u00e0"
    ],
    "PT": [
      "L\u00e1"
    ],
    "ES": [
      "All\u00ed"
    ],
    "EN": [
      "There"
    ]
  },
  {
    "IT": [
      "Questo"
    ],
    "FR": [
      "Ce ici"
    ],
    "RU": [
      "\u042d\u0442\u043e"
    ],
    "CA": [
      "Aix\u00f2"
    ],
    "PT": [
      "Isto"
    ],
    "ES": [
      "Esto"
    ],
    "EN": [
      "This"
    ]
  },
  {
    "IT": [
      "Quelo"
    ],
    "FR": [
      "Ce l\u00e0"
    ],
    "CA": [
      "All\u00f2"
    ],
    "PT": [
      "Isso, Aquilo"
    ],
    "ES": [
      "Eso, Aquello"
    ],
    "EN": [
      "That"
    ]
  },
  {
    "IT": [
      "Su"
    ],
    "FR": [
      "Dessus"
    ],
    "RU": [
      "\u0412\u0432\u0435\u0440\u0445"
    ],
    "CA": [
      "Adalt"
    ],
    "PT": [
      "Acima"
    ],
    "ES": [
      "Arriba"
    ],
    "EN": [
      "Up"
    ]
  },
  {
    "IT": [
      "Gi\u00f9"
    ],
    "FR": [
      "Dessous"
    ],
    "RU": [
      "\u0412\u043d\u0438\u0437"
    ],
    "CA": [
      "Abaix"
    ],
    "PT": [
      "Abaixo"
    ],
    "ES": [
      "Abajo"
    ],
    "EN": [
      "Down"
    ]
  },
  {
    "IT": [
      "Sinistra"
    ],
    "FR": [
      "Gauche"
    ],
    "RU": [
      "\u0421\u043b\u0435\u0432\u0430"
    ],
    "CA": [
      "Esquerra"
    ],
    "PT": [
      "Esquerda"
    ],
    "ES": [
      "Izquierda"
    ],
    "EN": [
      "Left"
    ]
  },
  {
    "IT": [
      "Destra"
    ],
    "FR": [
      "Droite"
    ],
    "RU": [
      "\u0421\u043f\u0440\u0430\u0432\u0430"
    ],
    "CA": [
      "Dreta"
    ],
    "PT": [
      "Direita"
    ],
    "ES": [
      "Derecha"
    ],
    "EN": [
      "Right"
    ]
  },
  {
    "IT": [
      "Avanti"
    ],
    "FR": [
      "Avant"
    ],
    "RU": [
      "\u041f\u0435\u0440\u0435\u0434"
    ],
    "CA": [
      "Endavant, Davant"
    ],
    "PT": [
      "Frente"
    ],
    "ES": [
      "Delante"
    ],
    "EN": [
      "Front"
    ]
  },
  {
    "IT": [
      "Dietro"
    ],
    "FR": [
      "Derri\u00e8re"
    ],
    "RU": [
      "\u0417\u0430"
    ],
    "CA": [
      "Endarrera, Darrera"
    ],
    "PT": [
      "Atr\u00e1s"
    ],
    "ES": [
      "Detr\u00e1s"
    ],
    "EN": [
      "Back"
    ]
  },
  {
    "IT": [
      "Entrada",
      "F"
    ],
    "FR": [
      "Entr\u00e9e",
      "F"
    ],
    "RU": [
      "\u0412\u0445\u043e\u0434",
      "M"
    ],
    "CA": [
      "Entrada",
      "F"
    ],
    "PT": [
      "Entrada",
      "F"
    ],
    "ES": [
      "Entrada",
      "F"
    ],
    "EN": [
      "Entry"
    ]
  },
  {
    "IT": [
      "Uscita",
      "F"
    ],
    "FR": [
      "Sortie",
      "F"
    ],
    "RU": [
      "\u0412\u044b\u0445\u043e\u0434",
      "M"
    ],
    "CA": [
      "Sortida",
      "F"
    ],
    "PT": [
      "Sa\u00edda",
      "F"
    ],
    "ES": [
      "Salida",
      "F"
    ],
    "EN": [
      "Exit"
    ]
  },
  {
    "IT": [
      "Prima colazione",
      "F"
    ],
    "FR": [
      "P\u00e9tit d\u00e9juner",
      "M"
    ],
    "RU": [
      "\u0417\u0430\u0432\u0442\u0440\u0430\u043a",
      "M"
    ],
    "CA": [
      "Esmorzar",
      "M"
    ],
    "PT": [
      "Caf\u00e9 da manh\u00e3",
      "M"
    ],
    "ES": [
      "Desayuno",
      "M"
    ],
    "EN": [
      "Breakfast"
    ]
  },
  {
    "IT": [
      "Pranzo",
      "M"
    ],
    "FR": [
      "D\u00e9juner",
      "M"
    ],
    "RU": [
      "\u041e\u0431\u0435\u0434",
      "M"
    ],
    "CA": [
      "Dinar",
      "M"
    ],
    "PT": [
      "Almo\u00e7o",
      "M"
    ],
    "ES": [
      "Comida",
      "F"
    ],
    "EN": [
      "Lunch"
    ]
  },
  {
    "IT": [
      "Cena",
      "F"
    ],
    "FR": [
      "D\u00eener",
      "M"
    ],
    "RU": [
      "\u0423\u0436\u0438\u043d",
      "M"
    ],
    "CA": [
      "Sopar",
      "M"
    ],
    "PT": [
      "Jantar",
      "M"
    ],
    "ES": [
      "Cena",
      "F"
    ],
    "EN": [
      "Dinner"
    ]
  },
  {
    "IT": [
      "Sempre"
    ],
    "FR": [
      "Toujours"
    ],
    "RU": [
      "\u0412\u0441\u0435\u0433\u0434\u0430"
    ],
    "CA": [
      "Sempre"
    ],
    "PT": [
      "Sempre"
    ],
    "ES": [
      "Siempre"
    ],
    "EN": [
      "Always"
    ]
  },
  {
    "IT": [
      "Mai"
    ],
    "FR": [
      "Jamais"
    ],
    "RU": [
      "\u041d\u0438\u043a\u043e\u0433\u0434\u0430"
    ],
    "CA": [
      "Mai"
    ],
    "PT": [
      "Nunca"
    ],
    "ES": [
      "Nunca, Jam\u00e1s"
    ],
    "EN": [
      "Never"
    ]
  },
  {
    "IT": [
      "Ieri",
      "M"
    ],
    "FR": [
      "Hier",
      "M"
    ],
    "RU": [
      "\u0412\u0447\u0435\u0440\u0430",
      "F"
    ],
    "CA": [
      "Ahir",
      "M"
    ],
    "PT": [
      "Ontem",
      "M"
    ],
    "ES": [
      "Ayer",
      "M"
    ],
    "EN": [
      "Yesterday"
    ]
  },
  {
    "IT": [
      "Oggi",
      "M"
    ],
    "FR": [
      "Aujourd'hui",
      "M"
    ],
    "RU": [
      "\u0421\u0435\u0433\u043e\u0434\u043d\u044f",
      "F"
    ],
    "CA": [
      "Avui",
      "M"
    ],
    "PT": [
      "Hoje",
      "M"
    ],
    "ES": [
      "Hoy",
      "M"
    ],
    "EN": [
      "Today"
    ]
  },
  {
    "IT": [
      "Domani",
      "M"
    ],
    "FR": [
      "Demain",
      "M"
    ],
    "RU": [
      "\u0417\u0430\u0432\u0442\u0440\u0430",
      "F"
    ],
    "CA": [
      "Dem\u00e0",
      "M"
    ],
    "PT": [
      "Amanh\u00e1",
      "M"
    ],
    "ES": [
      "Ma\u00f1ana (Pr\u00f3ximo d\u00eda)",
      "M"
    ],
    "EN": [
      "Tomorrow"
    ]
  },
  {
    "IT": [
      "Giorno",
      "M"
    ],
    "FR": [
      "Jour",
      "M"
    ],
    "RU": [
      "\u0414\u0435\u043d\u044c",
      "M"
    ],
    "CA": [
      "Dia",
      "M"
    ],
    "PT": [
      "Dia",
      "M"
    ],
    "ES": [
      "D\u00eda",
      "M"
    ],
    "EN": [
      "Day"
    ]
  },
  {
    "IT": [
      "Settimana",
      "F"
    ],
    "FR": [
      "Semaine",
      "F"
    ],
    "RU": [
      "\u041d\u0435\u0434\u0435\u043b\u044f",
      "F"
    ],
    "CA": [
      "Setmana",
      "F"
    ],
    "PT": [
      "Semana",
      "F"
    ],
    "ES": [
      "Semana",
      "F"
    ],
    "EN": [
      "Week"
    ]
  },
  {
    "IT": [
      "Fine settimana",
      "M"
    ],
    "FR": [
      "Weekend",
      "M"
    ],
    "RU": [
      "\u0412\u044b\u0445\u043e\u0434\u043d\u044b\u0435"
    ],
    "CA": [
      "Cap de setmana",
      "M"
    ],
    "PT": [
      "Fim de semana",
      "M"
    ],
    "ES": [
      "Fin de semana",
      "M"
    ],
    "EN": [
      "Weekend"
    ]
  },
  {
    "IT": [
      "Luned\u00ec",
      "M"
    ],
    "FR": [
      "Lundi",
      "M"
    ],
    "RU": [
      "\u041f\u043e\u043d\u0435\u0434\u0435\u043b\u044c\u043d\u0438\u043a",
      "M"
    ],
    "CA": [
      "Dilluns",
      "M"
    ],
    "PT": [
      "Segunda feira",
      "F"
    ],
    "ES": [
      "Lunes",
      "M"
    ],
    "EN": [
      "Monday"
    ]
  },
  {
    "IT": [
      "Marted\u00ec",
      "M"
    ],
    "FR": [
      "Mardi",
      "M"
    ],
    "RU": [
      "\u0412\u0442\u043e\u0440\u043d\u0438\u043a",
      "M"
    ],
    "CA": [
      "Dimarts",
      "M"
    ],
    "PT": [
      "Ter\u00e7a feira",
      "F"
    ],
    "ES": [
      "Martes",
      "M"
    ],
    "EN": [
      "Tuesday"
    ]
  },
  {
    "IT": [
      "Mercoled\u00ec",
      "M"
    ],
    "FR": [
      "Mercredi",
      "M"
    ],
    "RU": [
      "\u0421\u0440\u0435\u0434\u0430",
      "F"
    ],
    "CA": [
      "Dimecres",
      "M"
    ],
    "PT": [
      "Quarta feira",
      "F"
    ],
    "ES": [
      "Mi\u00e9rcoles",
      "M"
    ],
    "EN": [
      "Wednsday"
    ]
  },
  {
    "IT": [
      "Gioved\u00ec",
      "M"
    ],
    "FR": [
      "Jeudi",
      "M"
    ],
    "RU": [
      "\u0427\u0435\u0442\u0432\u0435\u0440\u0433",
      "M"
    ],
    "CA": [
      "Dijous",
      "M"
    ],
    "PT": [
      "Quinta feira",
      "F"
    ],
    "ES": [
      "Jueves",
      "M"
    ],
    "EN": [
      "Thursday"
    ]
  },
  {
    "IT": [
      "Venerd\u00ec",
      "M"
    ],
    "FR": [
      "Vendredi",
      "M"
    ],
    "RU": [
      "\u041f\u044f\u0442\u043d\u0438\u0446\u0430",
      "F"
    ],
    "CA": [
      "Divendres",
      "M"
    ],
    "PT": [
      "Sexta feira",
      "F"
    ],
    "ES": [
      "Viernes",
      "M"
    ],
    "EN": [
      "Friday"
    ]
  },
  {
    "IT": [
      "Sabato",
      "M"
    ],
    "FR": [
      "Samedi",
      "M"
    ],
    "RU": [
      "\u0421\u0443\u0431\u0431\u043e\u0442\u0430",
      "F"
    ],
    "CA": [
      "Dissabte",
      "M"
    ],
    "PT": [
      "S\u00e1bado",
      "M"
    ],
    "ES": [
      "S\u00e1bado",
      "M"
    ],
    "EN": [
      "Saturday"
    ]
  },
  {
    "IT": [
      "Domenica",
      "F"
    ],
    "FR": [
      "Dimanche",
      "M"
    ],
    "RU": [
      "\u0412\u043e\u0441\u043a\u0440\u0435\u0441\u0435\u043d\u044c\u0435",
      "N"
    ],
    "CA": [
      "Diumenge",
      "M"
    ],
    "PT": [
      "Domingo",
      "M"
    ],
    "ES": [
      "Domingo",
      "M"
    ],
    "EN": [
      "Sunday"
    ]
  },
  {
    "IT": [
      "Mese",
      "M"
    ],
    "FR": [
      "Mois",
      "M"
    ],
    "RU": [
      "\u041c\u0435\u0441\u044f\u0446",
      "M"
    ],
    "CA": [
      "Mes",
      "M"
    ],
    "PT": [
      "M\u00eas",
      "M"
    ],
    "ES": [
      "Mes",
      "M"
    ],
    "EN": [
      "Month"
    ]
  },
  {
    "IT": [
      "Gennaio",
      "M"
    ],
    "FR": [
      "Janvier",
      "M"
    ],
    "RU": [
      "\u042f\u043d\u0432\u0430\u0440\u044c",
      "M"
    ],
    "CA": [
      "Gener",
      "M"
    ],
    "PT": [
      "Janeiro",
      "M"
    ],
    "ES": [
      "Enero",
      "M"
    ],
    "EN": [
      "January"
    ]
  },
  {
    "IT": [
      "Febbraio",
      "M"
    ],
    "FR": [
      "F\u00e9vrier",
      "M"
    ],
    "RU": [
      "\u0424\u0435\u0432\u0440\u0430\u043b\u044c",
      "M"
    ],
    "CA": [
      "Febrer",
      "M"
    ],
    "PT": [
      "Fevereiro",
      "M"
    ],
    "ES": [
      "Febrero",
      "M"
    ],
    "EN": [
      "February"
    ]
  },
  {
    "IT": [
      "Marzo",
      "M"
    ],
    "FR": [
      "Mars",
      "M"
    ],
    "RU": [
      "\u041c\u0430\u0440\u0442",
      "M"
    ],
    "CA": [
      "Mar\u00e7",
      "M"
    ],
    "PT": [
      "Mar\u00e7o",
      "M"
    ],
    "ES": [
      "Marzo",
      "M"
    ],
    "EN": [
      "March"
    ]
  },
  {
    "IT": [
      "Aprile",
      "M"
    ],
    "FR": [
      "Avril",
      "M"
    ],
    "RU": [
      "\u0410\u043f\u0440\u0435\u043b\u044c",
      "M"
    ],
    "CA": [
      "Abril",
      "M"
    ],
    "PT": [
      "Abril",
      "M"
    ],
    "ES": [
      "Abril",
      "M"
    ],
    "EN": [
      "April"
    ]
  },
  {
    "IT": [
      "Maggio",
      "M"
    ],
    "FR": [
      "Mai",
      "M"
    ],
    "RU": [
      "\u041c\u0430\u0439",
      "M"
    ],
    "CA": [
      "Maig",
      "M"
    ],
    "PT": [
      "Maio",
      "M"
    ],
    "ES": [
      "Mayo",
      "M"
    ],
    "EN": [
      "May"
    ]
  },
  {
    "IT": [
      "Giugno",
      "M"
    ],
    "FR": [
      "Juin",
      "M"
    ],
    "RU": [
      "\u0418\u044e\u043d\u044c",
      "M"
    ],
    "CA": [
      "Juny",
      "M"
    ],
    "PT": [
      "Junho",
      "M"
    ],
    "ES": [
      "Junio",
      "M"
    ],
    "EN": [
      "June"
    ]
  },
  {
    "IT": [
      "Iuglio",
      "M"
    ],
    "FR": [
      "Juillet",
      "M"
    ],
    "RU": [
      "\u0418\u044e\u043b\u044c",
      "M"
    ],
    "CA": [
      "Juliol",
      "M"
    ],
    "PT": [
      "Julho",
      "M"
    ],
    "ES": [
      "Julio",
      "M"
    ],
    "EN": [
      "July"
    ]
  },
  {
    "IT": [
      "Agosto",
      "M"
    ],
    "FR": [
      "Ao\u00fbt",
      "M"
    ],
    "RU": [
      "\u0410\u0432\u0433\u0443\u0441\u0442",
      "M"
    ],
    "CA": [
      "Agost",
      "M"
    ],
    "PT": [
      "Agosto",
      "M"
    ],
    "ES": [
      "Agosto",
      "M"
    ],
    "EN": [
      "August"
    ]
  },
  {
    "IT": [
      "Settembre",
      "M"
    ],
    "FR": [
      "Septembre",
      "M"
    ],
    "RU": [
      "\u0421\u0435\u043d\u0442\u044f\u0431\u0440\u044c",
      "M"
    ],
    "CA": [
      "Setembre",
      "M"
    ],
    "PT": [
      "Setembro",
      "M"
    ],
    "ES": [
      "Septiembre",
      "M"
    ],
    "EN": [
      "September"
    ]
  },
  {
    "IT": [
      "Ottobre",
      "M"
    ],
    "FR": [
      "Octubre",
      "M"
    ],
    "RU": [
      "\u041e\u043a\u0442\u044f\u0431\u0440\u044c",
      "M"
    ],
    "CA": [
      "Octubre",
      "M"
    ],
    "PT": [
      "Outubro",
      "M"
    ],
    "ES": [
      "Octubre",
      "M"
    ],
    "EN": [
      "October"
    ]
  },
  {
    "IT": [
      "Novembre",
      "M"
    ],
    "FR": [
      "Novembre",
      "M"
    ],
    "RU": [
      "\u041d\u043e\u044f\u0431\u0440\u044c",
      "M"
    ],
    "CA": [
      "Novembre",
      "M"
    ],
    "PT": [
      "Novembro",
      "M"
    ],
    "ES": [
      "Noviembre",
      "M"
    ],
    "EN": [
      "November"
    ]
  },
  {
    "IT": [
      "Dicembre",
      "M"
    ],
    "FR": [
      "D\u00e9cembre",
      "M"
    ],
    "RU": [
      "\u0414\u0435\u043a\u0430\u0431\u0440\u044c",
      "M"
    ],
    "CA": [
      "Desembre",
      "M"
    ],
    "PT": [
      "Dezembro",
      "M"
    ],
    "ES": [
      "Diciembre",
      "M"
    ],
    "EN": [
      "December"
    ]
  },
  {
    "IT": [
      "Stagione",
      "F"
    ],
    "FR": [
      "Saison",
      "F"
    ],
    "RU": [
      "\u0421\u0435\u0437\u043e\u043d",
      "M"
    ],
    "CA": [
      "Estaci\u00f3",
      "F"
    ],
    "PT": [
      "Esta\u00e7\u00e3o",
      "F"
    ],
    "ES": [
      "Estaci\u00f3n (Mes)",
      "F"
    ],
    "EN": [
      "Season"
    ]
  },
  {
    "IT": [
      "Primavera",
      "F"
    ],
    "FR": [
      "Printemps",
      "M"
    ],
    "RU": [
      "\u0412\u0435\u0441\u043d\u0430",
      "F"
    ],
    "PT": [
      "Primavera",
      "F"
    ],
    "ES": [
      "Primavera",
      "F"
    ],
    "EN": [
      "Spring"
    ]
  },
  {
    "IT": [
      "Estate",
      "M"
    ],
    "FR": [
      "Et\u00ea",
      "M"
    ],
    "RU": [
      "\u041b\u0435\u0442\u043e",
      "N"
    ],
    "CA": [
      "Estiu",
      "M"
    ],
    "PT": [
      "Ver\u00e3o",
      "M"
    ],
    "ES": [
      "Verano",
      "M"
    ],
    "EN": [
      "Summer"
    ]
  },
  {
    "IT": [
      "Autunno",
      "M"
    ],
    "FR": [
      "Automne",
      "M"
    ],
    "RU": [
      "\u041e\u0441\u0435\u043d\u044c",
      "F"
    ],
    "CA": [
      "Tardor",
      "M"
    ],
    "PT": [
      "Outono",
      "M"
    ],
    "ES": [
      "Oto\u00f1o",
      "M"
    ],
    "EN": [
      "Autumn"
    ]
  },
  {
    "IT": [
      "Inverno",
      "M"
    ],
    "FR": [
      "Hiver",
      "M"
    ],
    "RU": [
      "\u0417\u0438\u043c\u0430",
      "F"
    ],
    "CA": [
      "Hivern",
      "F"
    ],
    "PT": [
      "Inverno",
      "M"
    ],
    "ES": [
      "Invierno",
      "M"
    ],
    "EN": [
      "Winter"
    ]
  },
  {
    "IT": [
      "Anno",
      "M"
    ],
    "FR": [
      "Ann\u00e9e",
      "M"
    ],
    "RU": [
      "\u0413\u043e\u0434",
      "M"
    ],
    "CA": [
      "Any",
      "M"
    ],
    "PT": [
      "Ano",
      "M"
    ],
    "ES": [
      "A\u00f1o",
      "M"
    ],
    "EN": [
      "Year"
    ]
  },
  {
    "IT": [
      "Essere"
    ],
    "FR": [
      "\u00catre"
    ],
    "CA": [
      "Ser"
    ],
    "PT": [
      "Ser"
    ],
    "ES": [
      "Ser"
    ],
    "EN": [
      "Be"
    ]
  },
  {
    "IT": [
      "\u00c8"
    ],
    "FR": [
      "Est"
    ],
    "CA": [
      "\u00c9s"
    ],
    "PT": [
      "\u00c9"
    ],
    "ES": [
      "Es"
    ],
    "EN": [
      "Is"
    ]
  },
  {
    "IT": [
      "Avere"
    ],
    "FR": [
      "Avoir"
    ],
    "CA": [
      "Tenir"
    ],
    "PT": [
      "Ter"
    ],
    "ES": [
      "Haber, Tener"
    ],
    "EN": [
      "Have"
    ]
  },
  {
    "IT": [
      "Vogliere"
    ],
    "FR": [
      "Vouloir"
    ],
    "RU": [
      "\u0425\u043e\u0442\u0435\u0442\u044c"
    ],
    "CA": [
      "Voler"
    ],
    "PT": [
      "Querer"
    ],
    "ES": [
      "Querer"
    ],
    "EN": [
      "Want"
    ]
  },
  {
    "IT": [
      "Potere"
    ],
    "FR": [
      "Povoir"
    ],
    "RU": [
      "\u0423\u043c\u0435\u0442\u044c, \u041c\u043e\u0447\u044c"
    ],
    "CA": [
      "Poguer"
    ],
    "PT": [
      "Poder"
    ],
    "ES": [
      "Poder"
    ],
    "EN": [
      "Can"
    ]
  },
  {
    "IT": [
      "Andare"
    ],
    "FR": [
      "Aller"
    ],
    "RU": [
      "\u0418\u0434\u0442\u0438, \u0425\u043e\u0434\u0438\u0442\u044c"
    ],
    "CA": [
      "Anar"
    ],
    "PT": [
      "Ir"
    ],
    "ES": [
      "Ir"
    ],
    "EN": [
      "Go"
    ]
  },
  {
    "IT": [
      "Venire"
    ],
    "FR": [
      "Venir"
    ],
    "RU": [
      "\u041f\u0440\u0438\u0439\u0442\u0438"
    ],
    "CA": [
      "Venir"
    ],
    "PT": [
      "Vir"
    ],
    "ES": [
      "Venir"
    ],
    "EN": [
      "Come"
    ]
  },
  {
    "IT": [
      "Tornare"
    ],
    "FR": [
      "Tourner"
    ],
    "RU": [
      "\u0412\u0435\u0440\u043d\u0438\u0441\u044c"
    ],
    "CA": [
      "Tornar"
    ],
    "PT": [
      "Voltar"
    ],
    "ES": [
      "Volver"
    ],
    "EN": [
      "Come back"
    ]
  },
  {
    "IT": [
      "Leggere"
    ],
    "FR": [
      "Lire"
    ],
    "RU": [
      "\u0427\u0438\u0442\u0430\u0442\u044c"
    ],
    "CA": [
      "Llegir"
    ],
    "PT": [
      "Ler"
    ],
    "ES": [
      "Leer"
    ],
    "EN": [
      "Read"
    ]
  },
  {
    "IT": [
      "Scrivere"
    ],
    "FR": [
      "\u00c9crire"
    ],
    "RU": [
      "\u041f\u0438\u0441\u0430\u0442\u044c"
    ],
    "CA": [
      "Escriure"
    ],
    "PT": [
      "Escrever"
    ],
    "ES": [
      "Escribir"
    ],
    "EN": [
      "Write"
    ]
  },
  {
    "IT": [
      "Annusare"
    ],
    "FR": [
      "Renifler"
    ],
    "RU": [
      "\u041d\u044e\u0445\u0430\u0442\u044c"
    ],
    "CA": [
      "Ensumar"
    ],
    "PT": [
      "Farejar"
    ],
    "ES": [
      "Olfatear"
    ],
    "EN": [
      "Sniff"
    ]
  },
  {
    "IT": [
      "Odorare"
    ],
    "FR": [
      "Sentir"
    ],
    "RU": [
      "\u041d\u0430\u0445\u043d\u0443\u0442\u044c"
    ],
    "CA": [
      "Olorar"
    ],
    "PT": [
      "Cheirar"
    ],
    "ES": [
      "Oler"
    ],
    "EN": [
      "Smell"
    ]
  },
  {
    "IT": [
      "Guardare"
    ],
    "FR": [
      "Regarder"
    ],
    "RU": [
      "\u0421\u043c\u043e\u0442\u0440\u0435\u0442\u044c"
    ],
    "CA": [
      "Mirar"
    ],
    "PT": [
      "Olhar"
    ],
    "ES": [
      "Mirar"
    ],
    "EN": [
      "Look, Watch"
    ]
  },
  {
    "IT": [
      "Vedere"
    ],
    "FR": [
      "Voir"
    ],
    "RU": [
      "\u0412\u0438\u0434\u0435\u0442\u044c"
    ],
    "CA": [
      "Veure"
    ],
    "PT": [
      "Ver"
    ],
    "ES": [
      "Ver"
    ],
    "EN": [
      "See"
    ]
  },
  {
    "IT": [
      "Cercare, Ricercare"
    ],
    "FR": [
      "Chercher, Rechercher"
    ],
    "RU": [
      "\u0418\u0441\u043a\u0430\u0442\u044c"
    ],
    "CA": [
      "Buscar, Cercar"
    ],
    "PT": [
      "Procurar"
    ],
    "ES": [
      "Buscar"
    ],
    "EN": [
      "Search"
    ]
  },
  {
    "IT": [
      "Trovare"
    ],
    "FR": [
      "Trouver"
    ],
    "RU": [
      "\u041d\u0430\u0445\u043e\u0434\u0438\u0442\u044c"
    ],
    "CA": [
      "Trobar"
    ],
    "PT": [
      "Encontrar, Achar"
    ],
    "ES": [
      "Encontrar"
    ],
    "EN": [
      "Find"
    ]
  },
  {
    "IT": [
      "Ascoltare"
    ],
    "FR": [
      "\u00c9couter"
    ],
    "RU": [
      "\u0421\u043b\u0443\u0448\u0430\u0442\u044c"
    ],
    "CA": [
      "Escoltar"
    ],
    "PT": [
      "Escutar"
    ],
    "ES": [
      "Escuchar"
    ],
    "EN": [
      "Listen"
    ]
  },
  {
    "IT": [
      "Sentire"
    ],
    "FR": [
      "Entendre"
    ],
    "RU": [
      "\u0421\u043b\u044b\u0448\u0430\u0442\u044c"
    ],
    "CA": [
      "Sento"
    ],
    "PT": [
      "Ouvir"
    ],
    "ES": [
      "O\u00edr"
    ],
    "EN": [
      "Hear"
    ]
  },
  {
    "IT": [
      "Parlare"
    ],
    "FR": [
      "Parler"
    ],
    "RU": [
      "\u0413\u043e\u0432\u043e\u0440\u0438\u0442\u044c"
    ],
    "CA": [
      "Parlar"
    ],
    "PT": [
      "Falar"
    ],
    "ES": [
      "Hablar"
    ],
    "EN": [
      "Speak"
    ]
  },
  {
    "IT": [
      "Capire"
    ],
    "FR": [
      "Comprendre"
    ],
    "RU": [
      "\u041f\u043e\u043d\u0438\u043c\u0430\u0442\u044c"
    ],
    "CA": [
      "Entendre"
    ],
    "PT": [
      "Entender, Comprender"
    ],
    "ES": [
      "Entender, Comprender"
    ],
    "EN": [
      "Understand"
    ]
  },
  {
    "IT": [
      "Imparare"
    ],
    "FR": [
      "Apprendre"
    ],
    "RU": [
      "\u0423\u0447\u0438\u0442\u044c"
    ],
    "CA": [
      "Aprendre"
    ],
    "PT": [
      "Aprender"
    ],
    "ES": [
      "Aprender"
    ],
    "EN": [
      "Learn"
    ]
  },
  {
    "IT": [
      "Ricordare"
    ],
    "FR": [
      "Souvenir"
    ],
    "RU": [
      "\u041f\u043e\u043c\u043d\u0438\u0442\u044c"
    ],
    "CA": [
      "Recordar, Enrecordar"
    ],
    "PT": [
      "Lembrar"
    ],
    "ES": [
      "Recordar"
    ],
    "EN": [
      "Remember"
    ]
  },
  {
    "IT": [
      "Dimenticare"
    ],
    "FR": [
      "Oublier"
    ],
    "RU": [
      "\u0417\u0430\u0431\u044b\u0432\u0430\u0442\u044c"
    ],
    "CA": [
      "Oblidar"
    ],
    "PT": [
      "Esquecer"
    ],
    "ES": [
      "Olvidar"
    ],
    "EN": [
      "Forget"
    ]
  },
  {
    "IT": [
      "Sapere, Conoscere"
    ],
    "FR": [
      "Savoir, Conna\u00eetre"
    ],
    "RU": [
      "\u0417\u043d\u0430\u0442\u044c"
    ],
    "CA": [
      "Sapiguer, Con\u00e8ixer"
    ],
    "PT": [
      "Saber, Conhecer"
    ],
    "ES": [
      "Saber, Conocer"
    ],
    "EN": [
      "Know"
    ]
  },
  {
    "IT": [
      "Pensare"
    ],
    "FR": [
      "Penser"
    ],
    "RU": [
      "\u0414\u0443\u043c\u0430\u0442\u044c"
    ],
    "CA": [
      "Pensar"
    ],
    "PT": [
      "Pensar, Achar"
    ],
    "ES": [
      "Pensar"
    ],
    "EN": [
      "Think"
    ]
  },
  {
    "IT": [
      "Credere"
    ],
    "FR": [
      "Croir"
    ],
    "RU": [
      "\u0412\u0435\u0440\u0438\u0442\u044c"
    ],
    "CA": [
      "Creure"
    ],
    "PT": [
      "Acreditar"
    ],
    "ES": [
      "Creer"
    ],
    "EN": [
      "Believe"
    ]
  },
  {
    "IT": [
      "Dormir"
    ],
    "FR": [
      "Dormir"
    ],
    "RU": [
      "\u0421\u043f\u0430\u0442\u044c"
    ],
    "CA": [
      "Dormir"
    ],
    "PT": [
      "Dormier"
    ],
    "ES": [
      "Dormir"
    ],
    "EN": [
      "Dormire"
    ]
  },
  {
    "IT": [
      "Lavorare"
    ],
    "FR": [
      "Travailler"
    ],
    "RU": [
      "\u0420\u0430\u0431\u043e\u0442\u0430\u0442\u044c"
    ],
    "CA": [
      "Treballar"
    ],
    "PT": [
      "Trabalhar"
    ],
    "ES": [
      "Trabajar"
    ],
    "EN": [
      "Work"
    ]
  },
  {
    "IT": [
      "Cucinare"
    ],
    "FR": [
      "Cuisiner"
    ],
    "RU": [
      "\u0413\u043e\u0442\u043e\u0432\u0438\u0442\u044c"
    ],
    "CA": [
      "Cuinar"
    ],
    "PT": [
      "Cozinhar"
    ],
    "ES": [
      "Cocinar"
    ],
    "EN": [
      "Cook"
    ]
  },
  {
    "IT": [
      "Mangiare"
    ],
    "FR": [
      "Manger"
    ],
    "RU": [
      "\u0415\u0441\u0442\u044c"
    ],
    "CA": [
      "Menjar"
    ],
    "PT": [
      "Comer"
    ],
    "ES": [
      "Comer"
    ],
    "EN": [
      "Eat"
    ]
  },
  {
    "IT": [
      "Bere"
    ],
    "FR": [
      "Boire"
    ],
    "RU": [
      "\u041f\u0438\u0442\u044c"
    ],
    "CA": [
      "Beure"
    ],
    "PT": [
      "Beber"
    ],
    "ES": [
      "Beber"
    ],
    "EN": [
      "Drink"
    ]
  },
  {
    "IT": [
      "Buono"
    ],
    "FR": [
      "Bon"
    ],
    "RU": [
      "\u0425\u043e\u0440\u043e\u0448\u0438\u0439"
    ],
    "CA": [
      "Bo"
    ],
    "PT": [
      "Bom"
    ],
    "ES": [
      "Bueno"
    ],
    "EN": [
      "Good"
    ]
  },
  {
    "IT": [
      "Cattivo"
    ],
    "FR": [
      "Mauvais"
    ],
    "RU": [
      "\u041f\u043b\u043e\u0445\u043e\u0439"
    ],
    "CA": [
      "Dolent"
    ],
    "PT": [
      "Ruim, Mau"
    ],
    "ES": [
      "Malo"
    ],
    "EN": [
      "Bad"
    ]
  },
  {
    "IT": [
      "Bello, Carino"
    ],
    "FR": [
      "Beau, Jolie"
    ],
    "RU": [
      "\u041a\u0440\u0430\u0441\u0438\u0432\u0438\u0439"
    ],
    "CA": [
      "Bonic, Maco"
    ],
    "PT": [
      "Bonito, Lindo"
    ],
    "ES": [
      "Bonito, Lindo"
    ],
    "EN": [
      "Beautiful, Pretty"
    ]
  },
  {
    "IT": [
      "Brutto"
    ],
    "FR": [
      "Lleig"
    ],
    "RU": [
      "\u0413\u043b\u0430\u0434\u043a\u0438\u0439"
    ],
    "CA": [
      "Lleig"
    ],
    "PT": [
      "Feio"
    ],
    "ES": [
      "Feo"
    ],
    "EN": [
      "Ugly"
    ]
  },
  {
    "IT": [
      "Piccolo"
    ],
    "FR": [
      "Petit"
    ],
    "RU": [
      "\u041c\u0430\u043b\u0435\u043d\u044c\u043a\u0438\u0439"
    ],
    "CA": [
      "Petit"
    ],
    "PT": [
      "Pequeno"
    ],
    "ES": [
      "Peque\u00f1o"
    ],
    "EN": [
      "Small"
    ]
  },
  {
    "IT": [
      "Grande"
    ],
    "FR": [
      "Grand"
    ],
    "RU": [
      "\u0411\u043e\u043b\u044c\u0448\u043e\u0439"
    ],
    "CA": [
      "Gran"
    ],
    "PT": [
      "Grande"
    ],
    "ES": [
      "Grande"
    ],
    "EN": [
      "Big"
    ]
  },
  {
    "IT": [
      "Corto"
    ],
    "FR": [
      "Court"
    ],
    "RU": [
      "\u041a\u043e\u0440\u043e\u0442\u043a\u0438\u0439"
    ],
    "CA": [
      "Curt"
    ],
    "PT": [
      "Curto"
    ],
    "ES": [
      "Corto"
    ],
    "EN": [
      "Short"
    ]
  },
  {
    "IT": [
      "Lungo"
    ],
    "FR": [
      "Long"
    ],
    "RU": [
      "\u0414\u043b\u0438\u043d\u043d\u044b\u0439"
    ],
    "CA": [
      "Llarg"
    ],
    "PT": [
      "Lungo"
    ],
    "ES": [
      "Largo"
    ],
    "EN": [
      "Long"
    ]
  },
  {
    "IT": [
      "Colore",
      "M"
    ],
    "FR": [
      "Coleur",
      "M"
    ],
    "RU": [
      "\u0426\u0432\u0435\u0442",
      "M"
    ],
    "CA": [
      "Color",
      "M"
    ],
    "PT": [
      "Cor",
      "M"
    ],
    "ES": [
      "Color",
      "M"
    ],
    "EN": [
      "Color"
    ]
  },
  {
    "IT": [
      "Colorato"
    ],
    "FR": [
      "Color\u00e9"
    ],
    "RU": [
      "\u041a\u0440\u0430\u0441\u043e\u0447\u043d\u044b\u0439"
    ],
    "CA": [
      "Colorit"
    ],
    "PT": [
      "Colorido"
    ],
    "ES": [
      "Colorido"
    ],
    "EN": [
      "Colorful"
    ]
  },
  {
    "IT": [
      "Bianco"
    ],
    "FR": [
      "Blanc"
    ],
    "RU": [
      "\u0411\u0435\u043b\u044b\u0439"
    ],
    "CA": [
      "Blanc"
    ],
    "PT": [
      "Branco"
    ],
    "ES": [
      "Blanco"
    ],
    "EN": [
      "White"
    ]
  },
  {
    "IT": [
      "Nero"
    ],
    "FR": [
      "Noir"
    ],
    "RU": [
      "\u0427\u0435\u0440\u043d\u044b\u0439"
    ],
    "CA": [
      "Negre"
    ],
    "PT": [
      "Preto"
    ],
    "ES": [
      "Negro"
    ],
    "EN": [
      "Black"
    ]
  },
  {
    "IT": [
      "Grigio"
    ],
    "FR": [
      "Gris"
    ],
    "RU": [
      "\u0421\u0435\u0440\u044b\u0439"
    ],
    "CA": [
      "Gris"
    ],
    "PT": [
      "Cinza"
    ],
    "ES": [
      "Gris"
    ],
    "EN": [
      "Grey"
    ]
  },
  {
    "IT": [
      "Rosso"
    ],
    "FR": [
      "Rouge"
    ],
    "RU": [
      "\u041a\u0440\u0430\u0441\u043d\u044b\u0439"
    ],
    "CA": [
      "Vermell"
    ],
    "PT": [
      "Vermelho"
    ],
    "ES": [
      "Rojo"
    ],
    "EN": [
      "Red"
    ]
  },
  {
    "IT": [
      "Giallo"
    ],
    "FR": [
      "Jaune"
    ],
    "RU": [
      "\u0416\u0435\u043b\u0442\u044b\u0439"
    ],
    "CA": [
      "Groc"
    ],
    "PT": [
      "Amarelo"
    ],
    "ES": [
      "Amarillo"
    ],
    "EN": [
      "Yellow"
    ]
  },
  {
    "IT": [
      "Verde"
    ],
    "FR": [
      "Vert"
    ],
    "RU": [
      "\u0417\u0435\u043b\u0435\u043d\u044b\u0439"
    ],
    "CA": [
      "Vert"
    ],
    "PT": [
      "Verde"
    ],
    "ES": [
      "Verde"
    ],
    "EN": [
      "Green"
    ]
  },
  {
    "IT": [
      "Azzurro, Blu"
    ],
    "FR": [
      "Bleu"
    ],
    "RU": [
      "\u0413\u043e\u043b\u0443\u0431"
    ],
    "CA": [
      "Blau"
    ],
    "PT": [
      "Azul"
    ],
    "ES": [
      "Azul"
    ],
    "EN": [
      "Blu"
    ]
  },
  {
    "IT": [
      "Marrone"
    ],
    "FR": [
      "Marron"
    ],
    "RU": [
      "\u041a\u043e\u0440\u0438\u0447\u043d\u0435\u0432\u044b\u0439"
    ],
    "CA": [
      "Marr\u00f3"
    ],
    "PT": [
      "Marrom"
    ],
    "ES": [
      "Marr\u00f3n"
    ],
    "EN": [
      "Brown"
    ]
  },
  {
    "IT": [
      "Arancione"
    ],
    "FR": [
      "Orange"
    ],
    "RU": [
      "\u041e\u0440\u0430\u043d\u0436\u0435\u0432\u044b\u0439"
    ],
    "CA": [
      "Taronja"
    ],
    "PT": [
      "Laranja"
    ],
    "ES": [
      "Naranja"
    ],
    "EN": [
      "Orange"
    ]
  },
  {
    "IT": [
      "Casa",
      "F"
    ],
    "FR": [
      "Maison",
      "F"
    ],
    "RU": [
      "\u0414\u043e\u043c",
      "M"
    ],
    "CA": [
      "Casa",
      "F"
    ],
    "PT": [
      "Casa",
      "F"
    ],
    "ES": [
      "Hogar, Casa"
    ],
    "EN": [
      "Home, House"
    ]
  },
  {
    "IT": [
      "Cane",
      "M"
    ],
    "FR": [
      "Chien",
      "M"
    ],
    "RU": [
      "\u0421\u043e\u0431\u0430\u043a\u0430",
      "F"
    ],
    "CA": [
      "Gos",
      "M"
    ],
    "PT": [
      "Cachorro",
      "M"
    ],
    "ES": [
      "Perro",
      "M"
    ],
    "EN": [
      "Dog"
    ]
  },
  {
    "IT": [
      "Gatto",
      "M"
    ],
    "FR": [
      "Chat",
      "M"
    ],
    "RU": [
      "\u041a\u043e\u0448\u043a\u0430",
      "F"
    ],
    "CA": [
      "Gat",
      "M"
    ],
    "PT": [
      "Gato",
      "M"
    ],
    "ES": [
      "Gato",
      "M"
    ],
    "EN": [
      "Cat"
    ]
  },
  {
    "IT": [
      "Pane",
      "M"
    ],
    "FR": [
      "Pain",
      "M"
    ],
    "RU": [
      "\u0425\u043b\u0435\u0431",
      "M"
    ],
    "CA": [
      "Pa",
      "M"
    ],
    "PT": [
      "P\u00e3o",
      "M"
    ],
    "ES": [
      "Pan",
      "M"
    ],
    "EN": [
      "Bread"
    ]
  },
  {
    "IT": [
      "Acqua",
      "F"
    ],
    "FR": [
      "Eau",
      "F"
    ],
    "RU": [
      "\u0412\u043e\u0434\u0430",
      "F"
    ],
    "CA": [
      "Aigua",
      "F"
    ],
    "PT": [
      "\u00c1gua",
      "F"
    ],
    "ES": [
      "Agua",
      "F"
    ],
    "EN": [
      "Water"
    ]
  },
  {
    "IT": [
      "Latte",
      "M"
    ],
    "FR": [
      "Lait",
      "M"
    ],
    "RU": [
      "\u041c\u043e\u043b\u043e\u043a\u043e",
      "N"
    ],
    "CA": [
      "Llet",
      "M"
    ],
    "PT": [
      "Leite",
      "M"
    ],
    "ES": [
      "Leche",
      "F"
    ],
    "EN": [
      "Milk"
    ]
  },
  {
    "IT": [
      "Burro",
      "M"
    ],
    "FR": [
      "Beurre",
      "M"
    ],
    "RU": [
      "\u041c\u0430\u0441\u043b\u043e",
      "N"
    ],
    "CA": [
      "Mantega",
      "F"
    ],
    "PT": [
      "Manteiga",
      "F"
    ],
    "ES": [
      "Mantequilla",
      "F"
    ],
    "EN": [
      "Butter"
    ]
  },
  {
    "IT": [
      "Mela",
      "F"
    ],
    "FR": [
      "Pomme",
      "F"
    ],
    "RU": [
      "\u042f\u0431\u043b\u043e\u043a\u043e",
      "N"
    ],
    "CA": [
      "Poma",
      "F"
    ],
    "PT": [
      "Ma\u00e7\u00e3",
      "F"
    ],
    "ES": [
      "Manzana",
      "F"
    ],
    "EN": [
      "Apple"
    ]
  },
  {
    "IT": [
      "Carne",
      "F"
    ],
    "FR": [
      "Viande",
      "F"
    ],
    "RU": [
      "\u041c\u044f\u0441\u043e",
      "N"
    ],
    "CA": [
      "Carn",
      "F"
    ],
    "PT": [
      "Carne",
      "F"
    ],
    "ES": [
      "Carne",
      "F"
    ],
    "EN": [
      "Meat"
    ]
  },
  {
    "IT": [
      "Pesce",
      "M"
    ],
    "FR": [
      "Poisson",
      "M"
    ],
    "RU": [
      "\u0420\u044b\u0431\u0430",
      "F"
    ],
    "CA": [
      "Peix",
      "M"
    ],
    "PT": [
      "Peixe",
      "M"
    ],
    "ES": [
      "Pez, Pescado",
      "M"
    ],
    "EN": [
      "Fish"
    ]
  },
  {
    "IT": [
      "Verdura",
      "F"
    ],
    "FR": [
      "L\u00e9gume",
      "F"
    ],
    "RU": [
      "\u041e\u0432\u043e\u0449",
      "M"
    ],
    "CA": [
      "Verdura, Llegum",
      "F"
    ],
    "PT": [
      "Verdura, Legume",
      "F"
    ],
    "ES": [
      "Verdura, Legumbre",
      "F"
    ],
    "EN": [
      "Vegetable"
    ]
  },
  {
    "IT": [
      "Frutta",
      "F"
    ],
    "FR": [
      "Fruit",
      "M"
    ],
    "RU": [
      "\u041f\u043b\u043e\u0434",
      "M"
    ],
    "CA": [
      "Fruita",
      "F"
    ],
    "PT": [
      "Fruta",
      "F"
    ],
    "ES": [
      "Fruta",
      "F"
    ],
    "EN": [
      "Fruit"
    ]
  },
  {
    "IT": [
      "Pomodoro",
      "M"
    ],
    "FR": [
      "Tomate",
      "F"
    ],
    "RU": [
      "\u041f\u043e\u043c\u0438\u0434\u043e\u0440",
      "M"
    ],
    "CA": [
      "Tom\u00e0quet",
      "M"
    ],
    "PT": [
      "Tomate",
      "M"
    ],
    "ES": [
      "Tomate",
      "M"
    ],
    "EN": [
      "Tomato"
    ]
  },
  {
    "IT": [
      "Meno male!"
    ],
    "FR": [
      "Hereusement!"
    ],
    "RU": [
      "\u042f \u0440\u0430\u0434, \u0421\u043b\u0430\u0432\u0430 \u0411\u043e\u0433\u0443!"
    ],
    "CA": [
      "Menys mal!"
    ],
    "PT": [
      "Menos mal!"
    ],
    "ES": [
      "Menos mal!"
    ],
    "EN": [
      "Luckily, Thank Goodness!"
    ]
  }
]